TeXtation/__init__.py
TeXtation/api_utils.py
TeXtation/gui_utils.py
TeXtation/main.py
TeXtation/settings.py
TeXtation-0.7.dist-info/METADATA
TeXtation-0.7.dist-info/WHEEL
TeXtation-0.7.dist-info/entry_points.txt
TeXtation-0.7.dist-info/top_level.txt
TeXtation-0.7.dist-info/RECORD
